{"/*":["X-Frame-Options: DENY","X-XSS-Protection: 1; mode=block","X-Content-Type-Options: nosniff","Referrer-Policy: same-origin"],"/styles.79064756ba25e44a2d03.css":["Cache-Control: public, max-age=31536000, immutable"],"/1bfc9850-d5e8f0286ecad4eb0520.js":["Cache-Control: public, max-age=31536000, immutable"],"/70b165ca-b56c6bd126107a3d1723.js":["Cache-Control: public, max-age=31536000, immutable"],"/commons-b8c5f74ac3122b407cfe.js":["Cache-Control: public, max-age=31536000, immutable"],"/83b623c4eada017ae1e852d567e48ab4e706c5a0-7b8e298dd9f46bd3472e.js":["Cache-Control: public, max-age=31536000, immutable"],"/component---src-pages-404-js-21c444c19a0bc0607d5e.js":["Cache-Control: public, max-age=31536000, immutable"],"/8c3c179e4f6655d9e21e291d4cd7446653c9060c-fbc26d45a21e4c8c8223.js":["Cache-Control: public, max-age=31536000, immutable"],"/b94d8c40bf6285130a733f77c1bf9b2b244856a7-a1ca37540a9702ad4e48.js":["Cache-Control: public, max-age=31536000, immutable"],"/component---src-pages-about-you-js-a49559ee00889f7e12e4.js":["Cache-Control: public, max-age=31536000, immutable"],"/0c428ae2-ca638871a4627f5403e5.js":["Cache-Control: public, max-age=31536000, immutable"],"/component---src-pages-index-js-220a0acdc545bb697817.js":["Cache-Control: public, max-age=31536000, immutable"],"/component---src-pages-us-js-66d45b91a59addcc1117.js":["Cache-Control: public, max-age=31536000, immutable"],"/component---src-pages-using-typescript-tsx-2e44a7d93b5b77691707.js":["Cache-Control: public, max-age=31536000, immutable"],"/webpack-runtime-0e6dbd9d403d0d70a760.js":["Cache-Control: public, max-age=31536000, immutable"],"/framework-89ddeb149991009fa125.js":["Cache-Control: public, max-age=31536000, immutable"],"/app-cbaaebc509746b011805.js":["Cache-Control: public, max-age=31536000, immutable"],"/static/*":["Cache-Control: public, max-age=31536000, immutable"],"/sw.js":["Cache-Control: public, max-age=0, must-revalidate"],"/404/":["Link: </webpack-runtime-0e6dbd9d403d0d70a760.js>; rel=preload; as=script; nopush","Link: </framework-89ddeb149991009fa125.js>; rel=preload; as=script; nopush","Link: </app-cbaaebc509746b011805.js>; rel=preload; as=script; nopush","Link: </1bfc9850-d5e8f0286ecad4eb0520.js>; rel=preload; as=script; nopush","Link: </70b165ca-b56c6bd126107a3d1723.js>; rel=preload; as=script; nopush","Link: </commons-b8c5f74ac3122b407cfe.js>; rel=preload; as=script; nopush","Link: </83b623c4eada017ae1e852d567e48ab4e706c5a0-7b8e298dd9f46bd3472e.js>; rel=preload; as=script; nopush","Link: </component---src-pages-404-js-21c444c19a0bc0607d5e.js>; rel=preload; as=script; nopush","Link: </page-data/app-data.json>; rel=preload; as=fetch; crossorigin; nopush","Link: </page-data/404/page-data.json>; rel=preload; as=fetch; crossorigin; nopush"],"/AboutYou/":["Link: </webpack-runtime-0e6dbd9d403d0d70a760.js>; rel=preload; as=script; nopush","Link: </framework-89ddeb149991009fa125.js>; rel=preload; as=script; nopush","Link: </app-cbaaebc509746b011805.js>; rel=preload; as=script; nopush","Link: </1bfc9850-d5e8f0286ecad4eb0520.js>; rel=preload; as=script; nopush","Link: </70b165ca-b56c6bd126107a3d1723.js>; rel=preload; as=script; nopush","Link: </commons-b8c5f74ac3122b407cfe.js>; rel=preload; as=script; nopush","Link: </8c3c179e4f6655d9e21e291d4cd7446653c9060c-fbc26d45a21e4c8c8223.js>; rel=preload; as=script; nopush","Link: </b94d8c40bf6285130a733f77c1bf9b2b244856a7-a1ca37540a9702ad4e48.js>; rel=preload; as=script; nopush","Link: </component---src-pages-about-you-js-a49559ee00889f7e12e4.js>; rel=preload; as=script; nopush","Link: </page-data/app-data.json>; rel=preload; as=fetch; crossorigin; nopush","Link: </page-data/AboutYou/page-data.json>; rel=preload; as=fetch; crossorigin; nopush"],"/":["Link: </webpack-runtime-0e6dbd9d403d0d70a760.js>; rel=preload; as=script; nopush","Link: </framework-89ddeb149991009fa125.js>; rel=preload; as=script; nopush","Link: </app-cbaaebc509746b011805.js>; rel=preload; as=script; nopush","Link: </1bfc9850-d5e8f0286ecad4eb0520.js>; rel=preload; as=script; nopush","Link: </70b165ca-b56c6bd126107a3d1723.js>; rel=preload; as=script; nopush","Link: </0c428ae2-ca638871a4627f5403e5.js>; rel=preload; as=script; nopush","Link: </commons-b8c5f74ac3122b407cfe.js>; rel=preload; as=script; nopush","Link: </8c3c179e4f6655d9e21e291d4cd7446653c9060c-fbc26d45a21e4c8c8223.js>; rel=preload; as=script; nopush","Link: </83b623c4eada017ae1e852d567e48ab4e706c5a0-7b8e298dd9f46bd3472e.js>; rel=preload; as=script; nopush","Link: </b94d8c40bf6285130a733f77c1bf9b2b244856a7-a1ca37540a9702ad4e48.js>; rel=preload; as=script; nopush","Link: </component---src-pages-index-js-220a0acdc545bb697817.js>; rel=preload; as=script; nopush","Link: </page-data/app-data.json>; rel=preload; as=fetch; crossorigin; nopush","Link: </page-data/index/page-data.json>; rel=preload; as=fetch; crossorigin; nopush"],"/Us/":["Link: </webpack-runtime-0e6dbd9d403d0d70a760.js>; rel=preload; as=script; nopush","Link: </framework-89ddeb149991009fa125.js>; rel=preload; as=script; nopush","Link: </app-cbaaebc509746b011805.js>; rel=preload; as=script; nopush","Link: </1bfc9850-d5e8f0286ecad4eb0520.js>; rel=preload; as=script; nopush","Link: </70b165ca-b56c6bd126107a3d1723.js>; rel=preload; as=script; nopush","Link: </commons-b8c5f74ac3122b407cfe.js>; rel=preload; as=script; nopush","Link: </8c3c179e4f6655d9e21e291d4cd7446653c9060c-fbc26d45a21e4c8c8223.js>; rel=preload; as=script; nopush","Link: </component---src-pages-us-js-66d45b91a59addcc1117.js>; rel=preload; as=script; nopush","Link: </page-data/app-data.json>; rel=preload; as=fetch; crossorigin; nopush","Link: </page-data/Us/page-data.json>; rel=preload; as=fetch; crossorigin; nopush"],"/using-typescript/":["Link: </webpack-runtime-0e6dbd9d403d0d70a760.js>; rel=preload; as=script; nopush","Link: </framework-89ddeb149991009fa125.js>; rel=preload; as=script; nopush","Link: </app-cbaaebc509746b011805.js>; rel=preload; as=script; nopush","Link: </1bfc9850-d5e8f0286ecad4eb0520.js>; rel=preload; as=script; nopush","Link: </70b165ca-b56c6bd126107a3d1723.js>; rel=preload; as=script; nopush","Link: </commons-b8c5f74ac3122b407cfe.js>; rel=preload; as=script; nopush","Link: </83b623c4eada017ae1e852d567e48ab4e706c5a0-7b8e298dd9f46bd3472e.js>; rel=preload; as=script; nopush","Link: </component---src-pages-using-typescript-tsx-2e44a7d93b5b77691707.js>; rel=preload; as=script; nopush","Link: </page-data/app-data.json>; rel=preload; as=fetch; crossorigin; nopush","Link: </page-data/using-typescript/page-data.json>; rel=preload; as=fetch; crossorigin; nopush"],"/404.html":["Link: </webpack-runtime-0e6dbd9d403d0d70a760.js>; rel=preload; as=script; nopush","Link: </framework-89ddeb149991009fa125.js>; rel=preload; as=script; nopush","Link: </app-cbaaebc509746b011805.js>; rel=preload; as=script; nopush","Link: </1bfc9850-d5e8f0286ecad4eb0520.js>; rel=preload; as=script; nopush","Link: </70b165ca-b56c6bd126107a3d1723.js>; rel=preload; as=script; nopush","Link: </commons-b8c5f74ac3122b407cfe.js>; rel=preload; as=script; nopush","Link: </83b623c4eada017ae1e852d567e48ab4e706c5a0-7b8e298dd9f46bd3472e.js>; rel=preload; as=script; nopush","Link: </component---src-pages-404-js-21c444c19a0bc0607d5e.js>; rel=preload; as=script; nopush","Link: </page-data/app-data.json>; rel=preload; as=fetch; crossorigin; nopush","Link: </page-data/404.html/page-data.json>; rel=preload; as=fetch; crossorigin; nopush"]}